odoo/addons/account_payment_residual_amount/README.rst
odoo/addons/account_payment_residual_amount/__init__.py
odoo/addons/account_payment_residual_amount/__manifest__.py
odoo/addons/account_payment_residual_amount/i18n/account_payment_residual_amount.pot
odoo/addons/account_payment_residual_amount/i18n/pt.po
odoo/addons/account_payment_residual_amount/i18n/pt_BR.po
odoo/addons/account_payment_residual_amount/models/__init__.py
odoo/addons/account_payment_residual_amount/models/account_payment.py
odoo/addons/account_payment_residual_amount/readme/CONTRIBUTORS.rst
odoo/addons/account_payment_residual_amount/readme/DESCRIPTION.rst
odoo/addons/account_payment_residual_amount/static/description/icon.png
odoo/addons/account_payment_residual_amount/static/description/index.html
odoo/addons/account_payment_residual_amount/static/description/payments_view.png
odoo/addons/account_payment_residual_amount/tests/__init__.py
odoo/addons/account_payment_residual_amount/tests/test_account_payment_residual_amount.py
odoo/addons/account_payment_residual_amount/views/account_payment_view.xml
odoo12_addon_account_payment_residual_amount-12.0.1.0.0.99.dev8.dist-info/METADATA
odoo12_addon_account_payment_residual_amount-12.0.1.0.0.99.dev8.dist-info/WHEEL
odoo12_addon_account_payment_residual_amount-12.0.1.0.0.99.dev8.dist-info/top_level.txt
odoo12_addon_account_payment_residual_amount-12.0.1.0.0.99.dev8.dist-info/RECORD
